codechecker_api/__init__.py
codechecker_api/Authentication_v6/__init__.py
codechecker_api/Authentication_v6/codeCheckerAuthentication.py
codechecker_api/Authentication_v6/constants.py
codechecker_api/Authentication_v6/ttypes.py
codechecker_api/Configuration_v6/__init__.py
codechecker_api/Configuration_v6/configurationService.py
codechecker_api/Configuration_v6/constants.py
codechecker_api/Configuration_v6/ttypes.py
codechecker_api/ProductManagement_v6/__init__.py
codechecker_api/ProductManagement_v6/codeCheckerProductService.py
codechecker_api/ProductManagement_v6/constants.py
codechecker_api/ProductManagement_v6/ttypes.py
codechecker_api/ServerInfo_v6/__init__.py
codechecker_api/ServerInfo_v6/constants.py
codechecker_api/ServerInfo_v6/serverInfoService.py
codechecker_api/ServerInfo_v6/ttypes.py
codechecker_api/codeCheckerDBAccess_v6/__init__.py
codechecker_api/codeCheckerDBAccess_v6/codeCheckerDBAccess.py
codechecker_api/codeCheckerDBAccess_v6/constants.py
codechecker_api/codeCheckerDBAccess_v6/ttypes.py
codechecker_api-6.39.0.dist-info/LICENSE
codechecker_api-6.39.0.dist-info/METADATA
codechecker_api-6.39.0.dist-info/WHEEL
codechecker_api-6.39.0.dist-info/top_level.txt
codechecker_api-6.39.0.dist-info/RECORD
