Metadata-Version: 2.1
Name: codechecker-api
Version: 6.39.0
Summary: Generated Python compatible API stubs for CodeChecker.
Home-page: https://github.com/Ericsson/codechecker
Author: CodeChecker Team (Ericsson)
License: UNKNOWN
Project-URL: Bug Reports, https://github.com/Ericsson/codechecker/issues
Project-URL: Source, https://github.com/Ericsson/codechecker/tree/master/web/api
Keywords: codechecker thrift api library
Platform: UNKNOWN
Classifier: Development Status :: 3 - Alpha
Classifier: Intended Audience :: Developers
Classifier: Programming Language :: Python :: 2
Classifier: Programming Language :: Python :: 3
Requires-Python: >=2.7,
Requires-Dist: codechecker-api-shared (==6.39.0)
Requires-Dist: thrift (==0.13.0)
